{
  "id": "services",
  "type": "SharedSlice",
  "name": "Services",
  "description": "Services",
  "variations": [
    {
      "id": "default",
      "name": "Default",
      "docURL": "...",
      "version": "sktwi1xtmkfgx8626",
      "description": "Services",
      "primary": {},
      "items": {
        "is_active": {
          "type": "Boolean",
          "config": {
            "label": "Is Active",
            "placeholder_false": "false",
            "placeholder_true": "true",
            "default_value": true
          }
        },
        "title": {
          "type": "StructuredText",
          "config": {
            "label": "Title",
            "placeholder": "",
            "allowTargetBlank": false,
            "single": "paragraph,strong"
          }
        },
        "description": {
          "type": "Text",
          "config": {
            "label": "Description",
            "placeholder": ""
          }
        },
        "image": {
          "type": "Image",
          "config": {
            "label": "Image",
            "constraint": {},
            "thumbnails": []
          }
        },
        "background_color": {
          "type": "Color",
          "config": {
            "label": "Background Color",
            "placeholder": ""
          }
        },
        "button_text": {
          "type": "Text",
          "config": {
            "label": "Button Text",
            "placeholder": ""
          }
        },
        "button_link": {
          "type": "Link",
          "config": {
            "label": "Button Link",
            "placeholder": "",
            "allowTargetBlank": true,
            "select": null
          }
        }
      },
      "imageUrl": "https://images.prismic.io/slice-machine/621a5ec4-0387-4bc5-9860-2dd46cbc07cd_default_ss.png?auto=compress,format"
    },
    {
      "id": "enterprise",
      "name": "Enterprise",
      "docURL": "...",
      "version": "sktwi1xtmkfgx8626",
      "description": "Services",
      "primary": {},
      "items": {
        "is_active": {
          "type": "Boolean",
          "config": {
            "label": "Is Active",
            "placeholder_false": "false",
            "placeholder_true": "true",
            "default_value": true
          }
        },
        "title": {
          "type": "StructuredText",
          "config": {
            "label": "Title",
            "placeholder": "",
            "allowTargetBlank": false,
            "single": "paragraph,strong"
          }
        },
        "description": {
          "type": "Text",
          "config": {
            "label": "Description",
            "placeholder": ""
          }
        },
        "image": {
          "type": "Image",
          "config": {
            "label": "Image",
            "constraint": {},
            "thumbnails": []
          }
        },
        "background_color": {
          "type": "Color",
          "config": {
            "label": "Background Color",
            "placeholder": ""
          }
        },
        "button_text": {
          "type": "Text",
          "config": {
            "label": "Button Text",
            "placeholder": ""
          }
        },
        "button_link": {
          "type": "Link",
          "config": {
            "label": "Button Link",
            "placeholder": "",
            "allowTargetBlank": true,
            "select": null
          }
        }
      },
      "imageUrl": "https://images.prismic.io/slice-machine/621a5ec4-0387-4bc5-9860-2dd46cbc07cd_default_ss.png?auto=compress,format"
    }
  ]
}